glide/__init__.py
glide/config.py
glide/constants.py
glide/exceptions.py
glide/logger.py
glide/protobuf_codec.py
glide/py.typed
glide/routes.py
glide/commands/__init__.py
glide/commands/batch.py
glide/commands/bitmap.py
glide/commands/command_args.py
glide/commands/core_options.py
glide/commands/sorted_set.py
glide/commands/stream.py
glide/commands/server_modules/ft.py
glide/commands/server_modules/glide_json.py
glide/commands/server_modules/json_batch.py
glide/commands/server_modules/ft_options/ft_aggregate_options.py
glide/commands/server_modules/ft_options/ft_constants.py
glide/commands/server_modules/ft_options/ft_create_options.py
glide/commands/server_modules/ft_options/ft_profile_options.py
glide/commands/server_modules/ft_options/ft_search_options.py
glide/commands/sync_commands/__init__.py
glide/commands/sync_commands/cluster_commands.py
glide/commands/sync_commands/core.py
glide/commands/sync_commands/standalone_commands.py
glide/protobuf/command_request_pb2.py
glide/protobuf/command_request_pb2.pyi
glide/protobuf/connection_request_pb2.py
glide/protobuf/connection_request_pb2.pyi
glide/protobuf/response_pb2.py
glide/protobuf/response_pb2.pyi
glide/sync/__init__.py
glide/sync/glide_client.py
glide/sync/libglide_ffi.so
test_valkey_glide_sync-0.1.2.dist-info/METADATA
test_valkey_glide_sync-0.1.2.dist-info/WHEEL
test_valkey_glide_sync-0.1.2.dist-info/top_level.txt
test_valkey_glide_sync-0.1.2.dist-info/RECORD
