Metadata-Version: 2.4
Name: test-valkey-glide-sync
Version: 0.1.2
Summary: Valkey GLIDE Sync client (CFFI-based)
Requires-Python: >=3.9
Requires-Dist: cffi>=1.0.0
Requires-Dist: protobuf>=6.20
